onionshare_cli/__init__.py
onionshare_cli/censorship.py
onionshare_cli/common.py
onionshare_cli/meek.py
onionshare_cli/mode_settings.py
onionshare_cli/onion.py
onionshare_cli/onionshare.py
onionshare_cli/resources/static/css/style.css
onionshare_cli/resources/static/img/ajax.gif
onionshare_cli/resources/static/img/favicon.ico
onionshare_cli/resources/static/img/logo.png
onionshare_cli/resources/static/img/logo_large.png
onionshare_cli/resources/static/img/web_file.png
onionshare_cli/resources/static/img/web_folder.png
onionshare_cli/resources/static/js/chat.js
onionshare_cli/resources/static/js/jquery-3.5.1.min.js
onionshare_cli/resources/static/js/receive.js
onionshare_cli/resources/static/js/send.js
onionshare_cli/resources/static/js/socket.io.js
onionshare_cli/resources/static/js/socket.io.min.js
onionshare_cli/resources/templates/403.html
onionshare_cli/resources/templates/404.html
onionshare_cli/resources/templates/405.html
onionshare_cli/resources/templates/500.html
onionshare_cli/resources/templates/chat.html
onionshare_cli/resources/templates/denied.html
onionshare_cli/resources/templates/listing.html
onionshare_cli/resources/templates/receive.html
onionshare_cli/resources/templates/send.html
onionshare_cli/resources/templates/thankyou.html
onionshare_cli/resources/torrc_template
onionshare_cli/resources/torrc_template-meek_lite_azure
onionshare_cli/resources/torrc_template-obfs4
onionshare_cli/resources/torrc_template-snowflake
onionshare_cli/resources/version.txt
onionshare_cli/resources/wordlist.txt
onionshare_cli/settings.py
onionshare_cli/web/__init__.py
onionshare_cli/web/chat_mode.py
onionshare_cli/web/receive_mode.py
onionshare_cli/web/send_base_mode.py
onionshare_cli/web/share_mode.py
onionshare_cli/web/web.py
onionshare_cli/web/website_mode.py
onionshare_cli-2.6.3.dist-info/METADATA
onionshare_cli-2.6.3.dist-info/WHEEL
onionshare_cli-2.6.3.dist-info/entry_points.txt
onionshare_cli-2.6.3.dist-info/RECORD
