Metadata-Version: 2.3
Name: onionshare_cli
Version: 2.6.3
Summary: OnionShare lets you securely and anonymously send and receive files. It works by starting a web server, making it accessible as a Tor onion service, and generating an unguessable web address so others can download files from you, or upload files to you. It does _not_ require setting up a separate server or using a third party file-sharing service.
License: GPLv3+
Author: Micah Lee
Author-email: micah@micahflee.com
Requires-Python: >=3.10,<3.13
Classifier: Environment :: Web Environment
Classifier: Framework :: Flask
Classifier: Intended Audience :: End Users/Desktop
Classifier: License :: OSI Approved :: GNU General Public License v3 or later (GPLv3+)
Classifier: License :: Other/Proprietary License
Classifier: Operating System :: OS Independent
Classifier: Programming Language :: Python :: 3
Classifier: Programming Language :: Python :: 3.10
Classifier: Programming Language :: Python :: 3.11
Classifier: Programming Language :: Python :: 3.12
Classifier: Topic :: Communications :: File Sharing
Classifier: Topic :: Security :: Cryptography
Requires-Dist: cffi (>=1.15.1,<2.0.0)
Requires-Dist: click
Requires-Dist: colorama
Requires-Dist: cython (>=3.0.2,<4.0.0)
Requires-Dist: eventlet
Requires-Dist: flask (==2.3.2)
Requires-Dist: flask-compress (>=1.13,<2.0)
Requires-Dist: flask-socketio (==5.3.4)
Requires-Dist: gevent (>=23.9.1,<24.0.0)
Requires-Dist: gevent-websocket
Requires-Dist: packaging (>=24)
Requires-Dist: psutil
Requires-Dist: pynacl
Requires-Dist: pysocks
Requires-Dist: qrcode (>=7.4.2,<8.0.0)
Requires-Dist: requests[socks]
Requires-Dist: setuptools (>=70.0.0)
Requires-Dist: stem (==1.8.1)
Requires-Dist: unidecode
Requires-Dist: urllib3 (>=2.2.2,<3.0.0)
Requires-Dist: waitress (>=3.0.1,<4.0.0)
Requires-Dist: werkzeug (==3.0.6)
Requires-Dist: wheel (>=0.41.2,<0.42.0)
